json2mqtt/__init__.py
json2mqtt/__main__.py
json2mqtt/commands.py
json2mqtt/mqtt.py
json2mqtt/scheduler.py
json2mqtt/schemas.py
json2mqtt/settings.py
json2mqtt-0.0.2.dist-info/entry_points.txt
json2mqtt-0.0.2.dist-info/LICENSE
json2mqtt-0.0.2.dist-info/WHEEL
json2mqtt-0.0.2.dist-info/METADATA
json2mqtt-0.0.2.dist-info/RECORD
