Metadata-Version: 2.1
Name: json2mqtt
Version: 0.0.2
Summary: Json2MQTT: A simple python daemon that crawls json apis and sends a selection of the data to a MQTT broker
Home-page: https://github.com/fliphess/json2mqtt
Author: Flip Hess
Author-email: flip@fliphess.com
Requires-Python: >=3.7
Classifier: License :: OSI Approved :: MIT License
Classifier: Programming Language :: Python :: 3.7
Classifier: Programming Language :: Python :: 3.8
Classifier: Programming Language :: Python :: 3.9
Requires-Dist: jmespath
Requires-Dist: jsonschema
Requires-Dist: multitimer
Requires-Dist: paho-mqtt
Requires-Dist: pid
Requires-Dist: requests
Requires-Dist: rfc3986-validator
Requires-Dist: ruamel.yaml
Requires-Dist: pytest ; extra == "test"
Requires-Dist: pytest-cov ; extra == "test"
Requires-Dist: pyproject-flake8 ; extra == "test"
Requires-Dist: mock ; extra == "test"
Provides-Extra: test
